README.md
setup.py
xeval/__init__.py
xeval/eval.py
xeval/metric.py
xeval.egg-info/PKG-INFO
xeval.egg-info/SOURCES.txt
xeval.egg-info/dependency_links.txt
xeval.egg-info/requires.txt
xeval.egg-info/top_level.txt