Metadata-Version: 2.1
Name: xeval
Version: 0.1.2
Summary: 深度学习评测包
Home-page: https://github.com/deng1fan
Author: deng1fan
Author-email: dengyifan@iie.ac.cn
Keywords: gpu,queuer,redis
Requires-Python: >=3.7
